{
    "name": "Logiks Dashboard",
    "version": "2.0.0",
    "status": "alpha",
    "type": "module",
    "package":"dashboard",
    "type": "module",
    "description": "Dashboard module for creating intriguing dashboards for logiks",
    "keywords": "logiks,modules,dashboard",
    "license": "MIT",
    "marketid": "",
    "homepage": "https://github.com/LogiksPlugins/dashboard",
    "bugs": "https://github.com/LogiksPlugins/dashboard/issues",
    "private": false,
    "dependencies": {
        "core": "+4.0.0",
    },
    "repository": {
        "type": "git",
        "url": "https://github.com/LogiksPlugins/dashboard.git"
    },
    "authors": [
        {
            "name": "OpenLogiks Team",
            "email": "admin@openlogiks.org",
            "authorid":"olgksadmin"
        }
    ]
}
